README.md
setup.py
hello_world_code/HelloWorldFile.py
hello_world_code/__init__.py
hello_world_lama_test.egg-info/PKG-INFO
hello_world_lama_test.egg-info/SOURCES.txt
hello_world_lama_test.egg-info/dependency_links.txt
hello_world_lama_test.egg-info/top_level.txt