Metadata-Version: 2.1
Name: hello-world-lama-test
Version: 0.0.1
Summary: test
Home-page: https://gist.github.com/lamoboos223/e1b8e3638e3b5eddd01ae0bf2d1c8d73
Author: Lama Alosaimi
License: MIT
Keywords: test
